ext_llm/__init__.py
ext_llm/context.py
ext_llm/extllm.py
ext_llm/scheduler.py
ext_llm/scheduler_statistic.py
ext_llm/scheduler_statistic_repository.py
ext_llm/llm/__init__.py
ext_llm/llm/concurrent_llm_client.py
ext_llm/llm/llm_client.py
ext_llm/llm/logging_llm_proxy.py
ext_llm/llm/logging_stream_proxy.py
ext_llm/llm/response.py
ext_llm/llm/response_repository.py
ext_llm/llm/stream.py
ext_llm/llm/aws/__init__.py
ext_llm/llm/aws/aws_llm_client.py
ext_llm/llm/aws/aws_stream.py
ext_llm/llm/groq/__init__.py
ext_llm/llm/groq/groq_llm_client.py
ext_llm/llm/groq/groq_stream.py
ext_llm/llm/mock-provider/__init__.py
ext_llm/llm/mock-provider/mock_llm_client.py
ext_llm/llm/mock-provider/mock_stream.py
ext_llm-0.1.16.dist-info/licenses/LICENSE
test/__init__.py
test/custom_provider_llm.py
test/showcase.py
test/showcase_with_scheduler.py
test/testing.py
ext_llm-0.1.16.dist-info/METADATA
ext_llm-0.1.16.dist-info/WHEEL
ext_llm-0.1.16.dist-info/top_level.txt
ext_llm-0.1.16.dist-info/RECORD
