Metadata-Version: 2.4
Name: ext_llm
Version: 0.1.16
Summary: A wrapper library to abstract common llm providers
Home-page: https://github.com/giovanni-grieco/ext_llm
Author: Giovanni Pio Grieco
Author-email: Giovanni Pio Grieco <gio.grieco@stud.uniroma3.it>
License-Expression: GPL-3.0
Project-URL: Homepage, https://github.com/giovanni-grieco/ext_llm
License-File: LICENSE
Requires-Dist: pyyaml
Requires-Dist: boto3
Requires-Dist: botocore
Requires-Dist: groq
Dynamic: author
Dynamic: home-page
Dynamic: license-file
